unxt_api/__init__.py
unxt_api/_version.py
unxt_api/py.typed
unxt_api/_src/__init__.py
unxt_api/_src/dimensions.py
unxt_api/_src/quantity.py
unxt_api/_src/units.py
unxt_api/_src/unitsystems.py
unxt_api-1.10.1.dist-info/METADATA
unxt_api-1.10.1.dist-info/WHEEL
unxt_api-1.10.1.dist-info/RECORD
